bokeh_sampledata/__init__.py
bokeh_sampledata/airport_routes.py
bokeh_sampledata/airports.py
bokeh_sampledata/anscombe.py
bokeh_sampledata/antibiotics.py
bokeh_sampledata/autompg.py
bokeh_sampledata/autompg2.py
bokeh_sampledata/browsers.py
bokeh_sampledata/commits.py
bokeh_sampledata/cows.py
bokeh_sampledata/daylight.py
bokeh_sampledata/degrees.py
bokeh_sampledata/emissions.py
bokeh_sampledata/forensic_glass.py
bokeh_sampledata/gapminder.py
bokeh_sampledata/glucose.py
bokeh_sampledata/haar_cascade.py
bokeh_sampledata/iris.py
bokeh_sampledata/les_mis.py
bokeh_sampledata/lincoln.py
bokeh_sampledata/movies_data.py
bokeh_sampledata/mtb.py
bokeh_sampledata/olympics2014.py
bokeh_sampledata/penguins.py
bokeh_sampledata/perceptions.py
bokeh_sampledata/periodic_table.py
bokeh_sampledata/population.py
bokeh_sampledata/py.typed
bokeh_sampledata/sample_geojson.py
bokeh_sampledata/sample_superstore.py
bokeh_sampledata/sea_surface_temperature.py
bokeh_sampledata/sprint.py
bokeh_sampledata/stocks.py
bokeh_sampledata/titanic.py
bokeh_sampledata/unemployment.py
bokeh_sampledata/unemployment1948.py
bokeh_sampledata/us_cities.py
bokeh_sampledata/us_counties.py
bokeh_sampledata/us_holidays.py
bokeh_sampledata/us_marriages_divorces.py
bokeh_sampledata/us_states.py
bokeh_sampledata/world_cities.py
bokeh_sampledata/_data/AAPL.csv
bokeh_sampledata/_data/CGM.csv
bokeh_sampledata/_data/FB.csv
bokeh_sampledata/_data/GOOG.csv
bokeh_sampledata/_data/IBM.csv
bokeh_sampledata/_data/MSFT.csv
bokeh_sampledata/_data/SampleSuperstore.csv
bokeh_sampledata/_data/USHolidays.ics
bokeh_sampledata/_data/US_Counties.csv
bokeh_sampledata/_data/US_Regions_State_Boundaries.csv.gz
bokeh_sampledata/_data/WPP2012_SA_DB03_POPULATION_QUINQUENNIAL.csv
bokeh_sampledata/_data/airports.csv
bokeh_sampledata/_data/airports.json
bokeh_sampledata/_data/anscombe.csv
bokeh_sampledata/_data/antibiotics.csv
bokeh_sampledata/_data/auto-mpg.csv
bokeh_sampledata/_data/auto-mpg2.csv
bokeh_sampledata/_data/browsers_nov_2013.csv
bokeh_sampledata-2024.2.dist-info/LICENSE.txt
bokeh_sampledata-2024.2.dist-info/METADATA
bokeh_sampledata-2024.2.dist-info/WHEEL
bokeh_sampledata-2024.2.dist-info/top_level.txt
bokeh_sampledata-2024.2.dist-info/RECORD
