Metadata-Version: 2.1
Name: bokeh_sampledata
Version: 2024.2
Summary: Sample datasets for Bokeh examples
Author: Bokeh Team
Author-email: info@bokeh.org
License: Copyright (c) Bokeh Contributors
Project-URL: homepage, https://bokeh.org
Project-URL: documentation, https://docs.bokeh.org
Project-URL: repository, https://github.com/bokeh/bokeh_sampledata
Classifier: Development Status :: 5 - Production/Stable
Classifier: Environment :: Console
Classifier: Intended Audience :: Developers
Classifier: Intended Audience :: End Users/Desktop
Classifier: License :: OSI Approved :: BSD License
Classifier: Programming Language :: Python
Classifier: Programming Language :: Python :: 3
Classifier: Programming Language :: Python :: 3 :: Only
Requires-Python: >=3.10
License-File: LICENSE.txt
Requires-Dist: icalendar
Requires-Dist: pandas>=1.2
